{
    "meta": {
        "pb": {
            "embed": {
                "main": {},
                "alpha": {},
                "team": {}
            }
        },
        "brands": {},
        "hs": {},
        "rw": {
            "params": {
                "public": {}
            },
            "embed": {}
        }
    },
    "salmon": {
        "salmon": {},
        "rewards": {},
        "on": {}
    },
    "game_lang": {
        "__COMMENT": {},
        "__unused": {
            "BigLaser": "センパイキャノン",
            "Bomb_MissionCurling": "カーリングボム",
            "Bomb_MissionRobo": "ロボットボム",
            "Bomb_MissionSplash": "スプラッシュボム",
            "Charger_MissionNormalLv0": "ヒーローチャージャー",
            "Charger_MissionNormalLv1": "ヒーローチャージャー",
            "MissileMissilePosition": "キャノン",
            "Roller_MissionBrushNormalLv0": "ヒーローブラシ",
            "Roller_MissionBrushNormalLv1": "ヒーローブラシ",
            "Roller_MissionNormalLv0": "ヒーローローラー",
            "Roller_MissionNormalLv1": "ヒーローローラー",
            "Shachihoko": "ガチホコ",
            "Shooter_BlasterMissionMiddleLv0": "ヒーローブラスター",
            "Shooter_BlasterMissionMiddleLv1": "ヒーローブラスター",
            "Shooter_MissionNormalLv0": "ヒーローシューター",
            "Shooter_MissionNormalLv1": "ヒーローシューター",
            "Shooter_MissionNormalLv2": "ヒーローシューター",
            "Slosher_MissionStrongLv0": "ヒーロースロッシャー",
            "Slosher_MissionStrongLv1": "ヒーロースロッシャー",
            "Spinner_MissionStandardLv0": "ヒーロースピナー",
            "Spinner_MissionStandardLv1": "ヒーロースピナー",
            "Twins_MissionNormalLv0": "ヒーローマニューバー",
            "Twins_MissionNormalLv1": "ヒーローマニューバー",
            "Umbrella_MissionNormalLv0": "ヒーローシェルター",
            "Umbrella_MissionNormalLv1": "ヒーローシェルター",
            "cPnt_2L": "ナワバリ\nバトル",
            "cVar_2L": "ガチ\nエリア",
            "cVcl_2L": "ガチ\nアサリ",
            "cVgl_2L": "ガチホコ\nバトル",
            "cVlf_2L": "ガチ\nヤグラ"
        },
        "brand": {
            "B00": "バトロイカ",
            "B01": "アイロニック",
            "B02": "クラーゲス",
            "B03": "ロッケンベルグ",
            "B04": "エゾッコ",
            "B05": "フォーリマ",
            "B06": "ホッコリー",
            "B07": "ホタックス",
            "B08": "ジモン",
            "B09": "シグレニ",
            "B10": "アロメ",
            "B11": "ヤコ",
            "B15": "アナアキ",
            "B16": "エンペリー",
            "B17": "タタキケンサキ",
            "B97": "クマサン商会",
            "B98": "アタリメイド",
            "B99": "amiibo"
        },
        "stat": {
            "Blaze": "連射力",
            "Charge": "チャージ速度",
            "Defence": "耐久力",
            "Explosion": "爆発力",
            "Mobility": "機動性",
            "PaintSpeed": "塗り進み速度",
            "Power": "攻撃力",
            "Range": "射程",
            "Weight": "軽さ"
        },
        "skill": {
            "Blank": "",
            "BombDamage_Reduction": "<:bddx:937213107250536489>爆風ダメージ軽減・改",
            "BombDistance_Up": "<:sbup:480391907952820224>サブ性能アップ",
            "ComeBack": "<:back:480361106418958336>カムバック",
            "DeathMarking": "<:haunt:480362082408071168>リベンジ",
            "EndAllUp": "<:last:480369613272776724>ラストスパート",
            "ExSkillDouble": "<:skdbl:937214085030895627>追加ギアパワー倍化",
            "Exorcist": "<:rpun:480374828747194369>復活ペナルティアップ",
            "HumanMove_Up": "<:runs:480375886575828992>ヒト移動速度アップ",
            "InkRecovery_Up": "<:irec:480362575238791170>インク回復力アップ",
            "JumpTime_Save": "<:qjmp:480374008504647703>スーパージャンプ時間短縮",
            "MainInk_Save": "<:msav:480364189995761664>インク効率アップ(メイン)",
            "MarkingTime_Reduction": "<:main:937213337366847508>メイン性能アップ",
            "MinorityUp": "<:tena:480394473264644115>逆境強化",
            "ObjectEffect_Up": "<:shred:480372472819089430>対物攻撃力アップ",
            "OpInkEffect_Reduction": "<:ires:480363715691020288>相手インク影響軽減",
            "RespawnSpecialGauge_Save": "<:spsv:480382942296932372>スペシャル減少量ダウン",
            "RespawnTime_Save": "<:qres:480373724479094804>復活時間短縮",
            "SomersaultLanding": "<:drop:480361804808192010>受け身術",
            "SpecialIncrease_Up": "<:scup:480376199453999104>スペシャル増加量アップ",
            "SpecialTime_Up": "<:spup:480381557618769931>スペシャル性能アップ",
            "SquidMoveSpatter_Reduction": "<:hide:480371545626378264>イカニンジャ",
            "SquidMove_Up": "<:swim:480393311413338122>イカダッシュ速度アップ",
            "StartAllUp": "<:open:480373410048770078>スタートダッシュ",
            "SubInk_Save": "<:sbsv:480365468423684106>インク効率アップ(サブ)",
            "SuperJumpSign_Hide": "<:jump:480383328214843393>ステルスジャンプ",
            "ThermalInk": "<:therm:480394726562988042>サーマルインク",
            "Unknown": "<:mystery:457050117694816257>"
        },
        "__skill_explain": {
            "SE_Blank": "",
            "SE_BombDamage_Reduction": "メインウェポン以外の爆発で\n受けるダメージと、位置を発見\nしてくる攻撃の効果を軽減します。",
            "SE_BombDistance_Up": "サブウェポンの性能が\nアップします。",
            "SE_ComeBack": "プレイヤーがやられて復帰後、\nしばらくの間、一部の能力が\nかなりアップします。",
            "SE_DeathMarking": "復活したとき、\n自分を倒した相手の位置が\n遠くから見えるようになります。",
            "SE_EndAllUp": "対戦終了の３０カウント前から\nインク効率とインク回復速度が\nかなりアップします。",
            "SE_ExSkillDouble": "このギアについている\n追加ギアパワーを\n１つで２コ分の効果にします。",
            "SE_Exorcist": "自プレイヤーと倒した相手の\nスペシャル減少量と\n復活時間が増えます。",
            "SE_HumanMove_Up": "ヒト状態の移動速度が\nアップします。",
            "SE_InkRecovery_Up": "インクタンク回復速度が\nアップします。",
            "SE_JumpTime_Save": "スーパージャンプの時間が\n短くなります。",
            "SE_MainInk_Save": "メインウェポンの\n消費インク量が\n少なくなります。",
            "SE_MarkingTime_Reduction": "[\u000e\u0004\u0000\u0004\u0000촀]\n\u000e\u0004\u0005\u0000",
            "SE_MarkingTime_Reduction_Default": "メインウェポンの性能が\nアップします。",
            "SE_MinorityUp": "自チームの人数が相手チーム\nより少ない場合、少しずつ\nスペシャルゲージが増えます。",
            "SE_ObjectEffect_Up": "プレイヤー以外の物体に対して\n攻撃したときのダメージを\n増やします。",
            "SE_OpInkEffect_Reduction": "相手のインクをふんだ時の\nダメージや移動速度の\n減少が少なくなります。",
            "SE_RespawnSpecialGauge_Save": "プレイヤーがやられた時の\nスペシャルゲージの減少量が\n少なくなります。",
            "SE_RespawnTime_Save": "相手を一人も倒せないまま\n連続でやられた時、\n復活時間が短くなります。",
            "SE_SomersaultLanding": "スーパージャンプ着地時に\nスティックをたおしておくと\n着地と同時に前転します。",
            "SE_SpecialIncrease_Up": "スペシャルゲージの増加量が\nアップします。",
            "SE_SpecialTime_Up": "スペシャルウェポンの性能が\nアップします。",
            "SE_SquidMoveSpatter_Reduction": "地面をイカダッシュした時に\nインクが飛び散らなくなるが、\n移動速度が少しダウンします。",
            "SE_SquidMove_Up": "イカダッシュ時の移動速度が\nアップします。",
            "SE_StartAllUp": "対戦開始から３０カウントの間\n移動に関する効果が\nかなりアップします。",
            "SE_SubInk_Save": "サブウェポンの消費インク量が\n少なくなります。",
            "SE_SuperJumpSign_Hide": "スーパージャンプの着地点を\n示すマーカーが、はなれた場所\nから見えなくなります。",
            "SE_ThermalInk": "メインウェポンの弾を直接\n当てた相手が、しばらくの間、\n遠くから見えるようになります。",
            "SE_Unknown": "ギアをバトルで使用して\nケイケン値をためると\nギアパワーが解放されます。"
        },
        "weapon_main": {
            "Charger_CoopSpark": "クマサン印のチャージャー",
            "Charger_Keeper_00": "ソイチューバー",
            "Charger_Keeper_01": "ソイチューバーカスタム",
            "Charger_Light_00": "14式竹筒銃・甲",
            "Charger_Light_01": "14式竹筒銃・乙",
            "Charger_Light_02": "14式竹筒銃・丙",
            "Charger_LongScope_00": "4Kスコープ",
            "Charger_LongScope_01": "4Kスコープカスタム",
            "Charger_Long_00": "リッター4K",
            "Charger_Long_01": "リッター4Kカスタム",
            "Charger_NormalScope_00": "スプラスコープ",
            "Charger_NormalScope_01": "スプラスコープコラボ",
            "Charger_NormalScope_02": "スプラスコープベッチュー",
            "Charger_Normal_00": "スプラチャージャー",
            "Charger_Normal_01": "スプラチャージャーコラボ",
            "Charger_Normal_02": "スプラチャージャーベッチュー",
            "Charger_Normal_H": "ヒーローチャージャー レプリカ",
            "Charger_Quick_00": "スクイックリンα",
            "Charger_Quick_01": "スクイックリンβ",
            "Charger_Quick_02": "スクイックリンγ",
            "Roller_BrushMini_00": "パブロ",
            "Roller_BrushMini_01": "パブロ・ヒュー",
            "Roller_BrushMini_02": "パーマネント・パブロ",
            "Roller_BrushNormal_00": "ホクサイ",
            "Roller_BrushNormal_01": "ホクサイ・ヒュー",
            "Roller_BrushNormal_02": "ホクサイベッチュー",
            "Roller_BrushNormal_H": "ヒーローブラシ レプリカ",
            "Roller_Compact_00": "カーボンローラー",
            "Roller_Compact_01": "カーボンローラーデコ",
            "Roller_Heavy_00": "ダイナモローラー",
            "Roller_Heavy_01": "ダイナモローラーテスラ",
            "Roller_Heavy_02": "ダイナモローラーベッチュー",
            "Roller_Hunter_00": "ヴァリアブルローラー",
            "Roller_Hunter_01": "ヴァリアブルローラーフォイル",
            "Roller_Normal_00": "スプラローラー",
            "Roller_Normal_01": "スプラローラーコラボ",
            "Roller_Normal_02": "スプラローラーベッチュー",
            "Roller_Normal_H": "ヒーローローラー レプリカ",
            "Shooter_BlasterCoopBurst": "クマサン印のブラスター",
            "Shooter_BlasterLightLong_00": "Rブラスターエリート",
            "Shooter_BlasterLightLong_01": "Rブラスターエリートデコ",
            "Shooter_BlasterLightShort_00": "クラッシュブラスター",
            "Shooter_BlasterLightShort_01": "クラッシュブラスターネオ",
            "Shooter_BlasterLight_00": "ラピッドブラスター",
            "Shooter_BlasterLight_01": "ラピッドブラスターデコ",
            "Shooter_BlasterLight_02": "ラピッドブラスターベッチュー",
            "Shooter_BlasterLong_00": "ロングブラスター",
            "Shooter_BlasterLong_01": "ロングブラスターカスタム",
            "Shooter_BlasterLong_02": "ロングブラスターネクロ",
            "Shooter_BlasterMiddle_00": "ホットブラスター",
            "Shooter_BlasterMiddle_01": "ホットブラスターカスタム",
            "Shooter_BlasterMiddle_H": "ヒーローブラスター レプリカ",
            "Shooter_BlasterShort_00": "ノヴァブラスター",
            "Shooter_BlasterShort_01": "ノヴァブラスターネオ",
            "Shooter_BlasterShort_02": "ノヴァブラスターベッチュー",
            "Shooter_Blaze_00": "プロモデラーMG",
            "Shooter_Blaze_01": "プロモデラーRG",
            "Shooter_Blaze_02": "プロモデラーPG",
            "Shooter_Expert_00": "プライムシューター",
            "Shooter_Expert_01": "プライムシューターコラボ",
            "Shooter_Expert_02": "プライムシューターベッチュー",
            "Shooter_First_00": "わかばシューター",
            "Shooter_First_01": "もみじシューター",
            "Shooter_First_02": "おちばシューター",
            "Shooter_Flash_00": "ボトルガイザー",
            "Shooter_Flash_01": "ボトルガイザーフォイル",
            "Shooter_Gravity_00": ".52ガロン",
            "Shooter_Gravity_01": ".52ガロンデコ",
            "Shooter_Gravity_02": ".52ガロンベッチュー",
            "Shooter_Heavy_00": ".96ガロン",
            "Shooter_Heavy_01": ".96ガロンデコ",
            "Shooter_Long_00": "ジェットスイーパー",
            "Shooter_Long_01": "ジェットスイーパーカスタム",
            "Shooter_Normal_00": "スプラシューター",
            "Shooter_Normal_01": "スプラシューターコラボ",
            "Shooter_Normal_02": "スプラシューターベッチュー",
            "Shooter_Normal_H": "ヒーローシューター レプリカ",
            "Shooter_Normal_Oct": "オクタシューター レプリカ",
            "Shooter_Precision_00": "シャープマーカー",
            "Shooter_Precision_01": "シャープマーカーネオ",
            "Shooter_QuickMiddle_00": "N-ZAP85",
            "Shooter_QuickMiddle_01": "N-ZAP89",
            "Shooter_QuickMiddle_02": "N-ZAP83",
            "Shooter_Short_00": "ボールドマーカー",
            "Shooter_Short_01": "ボールドマーカーネオ",
            "Shooter_Short_02": "ボールドマーカー7",
            "Shooter_TripleMiddle_00": "H3リールガン",
            "Shooter_TripleMiddle_01": "H3リールガンD",
            "Shooter_TripleMiddle_02": "H3リールガンチェリー",
            "Shooter_TripleQuick_00": "L3リールガン",
            "Shooter_TripleQuick_01": "L3リールガンD",
            "Shooter_TripleQuick_02": "L3リールガンベッチュー",
            "Slosher_Bathtub_00": "オーバーフロッシャー",
            "Slosher_Bathtub_01": "オーバーフロッシャーデコ",
            "Slosher_CoopVase": "クマサン印のスロッシャー",
            "Slosher_Diffusion_00": "ヒッセン",
            "Slosher_Diffusion_01": "ヒッセン・ヒュー",
            "Slosher_Launcher_00": "スクリュースロッシャー",
            "Slosher_Launcher_01": "スクリュースロッシャーネオ",
            "Slosher_Launcher_02": "スクリュースロッシャーベッチュー",
            "Slosher_Strong_00": "バケットスロッシャー",
            "Slosher_Strong_01": "バケットスロッシャーデコ",
            "Slosher_Strong_02": "バケットスロッシャーソーダ",
            "Slosher_Strong_H": "ヒーロースロッシャー レプリカ",
            "Slosher_Washtub_00": "エクスプロッシャー",
            "Slosher_Washtub_01": "エクスプロッシャーカスタム",
            "Spinner_Downpour_00": "クーゲルシュライバー",
            "Spinner_Downpour_01": "クーゲルシュライバー・ヒュー",
            "Spinner_Hyper_00": "ハイドラント",
            "Spinner_Hyper_01": "ハイドラントカスタム",
            "Spinner_Quick_00": "スプラスピナー",
            "Spinner_Quick_01": "スプラスピナーコラボ",
            "Spinner_Quick_02": "スプラスピナーベッチュー",
            "Spinner_Serein_00": "ノーチラス47",
            "Spinner_Serein_01": "ノーチラス79",
            "Spinner_Standard_00": "バレルスピナー",
            "Spinner_Standard_01": "バレルスピナーデコ",
            "Spinner_Standard_02": "バレルスピナーリミックス",
            "Spinner_Standard_H": "ヒーロースピナー レプリカ",
            "Twins_Dual_00": "デュアルスイーパー",
            "Twins_Dual_01": "デュアルスイーパーカスタム",
            "Twins_Gallon_00": "ケルビン525",
            "Twins_Gallon_01": "ケルビン525デコ",
            "Twins_Gallon_02": "ケルビン525ベッチュー",
            "Twins_Normal_00": "スプラマニューバー",
            "Twins_Normal_01": "スプラマニューバーコラボ",
            "Twins_Normal_02": "スプラマニューバーベッチュー",
            "Twins_Normal_H": "ヒーローマニューバー レプリカ",
            "Twins_Short_00": "スパッタリー",
            "Twins_Short_01": "スパッタリー・ヒュー",
            "Twins_Short_02": "スパッタリークリア",
            "Twins_Stepper_00": "クアッドホッパーブラック",
            "Twins_Stepper_01": "クアッドホッパーホワイト",
            "Umbrella_Compact_00": "スパイガジェット",
            "Umbrella_Compact_01": "スパイガジェットソレーラ",
            "Umbrella_Compact_02": "スパイガジェットベッチュー",
            "Umbrella_CoopAutoAssault": "クマサン印のシェルター",
            "Umbrella_Normal_00": "パラシェルター",
            "Umbrella_Normal_01": "パラシェルターソレーラ",
            "Umbrella_Normal_H": "ヒーローシェルター レプリカ",
            "Umbrella_Wide_00": "キャンピングシェルター",
            "Umbrella_Wide_01": "キャンピングシェルターソレーラ",
            "Umbrella_Wide_02": "キャンピングシェルターカーモ"
        },
        "weapon_sub": {
            "Bomb_Curling": "<:curling:451732483688497152>カーリングボム",
            "Bomb_Piyo": "<:fizzy:497394302595497984>タンサンボム",
            "Bomb_Quick": "<:burst:451732329153691648>クイックボム",
            "Bomb_Robo": "<:auto:451732432740286464>ロボットボム",
            "Bomb_Splash": "<:splat:451732998589644800>スプラッシュボム",
            "Bomb_Suction": "<:suction:451733156656316416>キューバンボム",
            "Bomb_Tako": "<:torpedo:510207376985423882>トーピード",
            "Flag": "<:beakon:451733111433068557>ジャンプビーコン",
            "PointSensor": "<:pointsensor:451732891727036416>ポイントセンサー",
            "PoisonFog": "<:mist:451733194149199873>ポイズンミスト",
            "Shield": "<:wall:451732942847213568>スプラッシュシールド",
            "Sprinkler": "<:sprinkler:451733051030896661>スプリンクラー",
            "TimerTrap": "<:mine:451732593054973952>トラップ"
        },
        "weapon_special": {
            "AquaBall": "<:baller:451733454154104842>イカスフィア",
            "Jetpack": "<:inkjet:451733714712657921>ジェットパック",
            "LauncherCurling": "<:curlinglauncher:451734750307287041>カーリングボムピッチャー",
            "LauncherQuick": "<:burstlauncher:451735283529023490>クイックボムピッチャー",
            "LauncherRobo": "<:autolauncher:451734905009995807>ロボボムピッチャー",
            "LauncherSplash": "<:splatlauncher:451733512232632320>スプラッシュボムピッチャー",
            "LauncherSuction": "<:suctionlauncher:451734826639425536>キューバンボムピッチャー",
            "RainCloud": "<:storm:451734059991826452>アメフラシ",
            "SuperArmor": "<:armour:451733645187743775>インクアーマー",
            "SuperBall": "<:booyah:497394472146042881>ナイスダマ",
            "SuperBubble": "<:bubble:451733595829174273>バブルランチャー",
            "SuperLanding": "<:splashdown:451734463332876289>スーパーチャクチ",
            "SuperMissile": "<:missiles:451734631775993876>マルチミサイル",
            "SuperStamp": "<:stamp:509782668016091189>ウルトラハンコ",
            "WaterCutter": "<:stingray:451734582258171904>ハイパープレッサー"
        },
        "clothes_head": {
            "Hed_ACC001": "カイザーカフ",
            "Hed_AMB000": "イカパッチン",
            "Hed_AMB001": "サムライヘルメット",
            "Hed_AMB002": "パワードマスク",
            "Hed_AMB003": "イカクリップ",
            "Hed_AMB004": "イカカゲマスク",
            "Hed_AMB005": "パワードマスク オリジン",
            "Hed_AMB006": "ヒメイトクラウン",
            "Hed_AMB007": "イイダチヘッドホン",
            "Hed_AMB008": "エンチャントハット",
            "Hed_AMB009": "タコティカルなヘルム",
            "Hed_AMB010": "ひれおくん",
            "Hed_CAP000": "ウーニーズBBキャップ",
            "Hed_CAP001": "キャンプキャップ",
            "Hed_CAP002": "ヤコメッシュ",
            "Hed_CAP003": "ビバレッジキャップ",
            "Hed_CAP004": "チドリキャップ",
            "Hed_CAP005": "イカベーダーキャップ",
            "Hed_CAP006": "カモメッシュ",
            "Hed_CAP007": "5パネルキャップ",
            "Hed_CAP008": "エゾッコメッシュ",
            "Hed_CAP009": "バックワードキャップ",
            "Hed_CAP010": "2ラインメッシュ",
            "Hed_CAP011": "ジェットキャップ",
            "Hed_CAP012": "テッカサイクルキャップ",
            "Hed_CAP014": "チャリキング帽",
            "Hed_CAP015": "でんせつのぼうし",
            "Hed_CAP018": "ロングビルキャップ",
            "Hed_CAP019": "キングフリップメッシュ",
            "Hed_CAP020": "ヒッコリーワークキャップ",
            "Hed_CAP021": "ウールウーニーズクラシック",
            "Hed_CAP023": "クラゲーダーキャップ",
            "Hed_CAP024": "ハウスタグデニムCAP",
            "Hed_CAP025": "フグハンチング",
            "Hed_CAP026": "ドゥーラグキャップガサネ",
            "Hed_CAP027": "フライトぼう",
            "Hed_COP100": "ヘッドライトヘルム",
            "Hed_COP101": "ダストブロッカー 2.5",
            "Hed_COP102": "アイアンマスカレイド",
            "Hed_COP103": "ガーディアンアーミーハット",
            "Hed_COP104": "ゾネスティックスコープ",
            "Hed_COP105": "レジェンドのぼうし",
            "Hed_COP106": "オーシャンズヘルム",
            "Hed_COP107": "アセストップソシナ",
            "Hed_COP108": "スペボウ レプリカ",
            "Hed_COP109": "マリリンハットウィズピンズ",
            "Hed_CRC000": "メカヘッド・HTR",
            "Hed_EYE000": "クロブチ レトロ",
            "Hed_EYE001": "スプラッシュゴーグル",
            "Hed_EYE002": "パイロットゴーグル",
            "Hed_EYE003": "イロメガネ",
            "Hed_EYE004": "アローバンド ブラック",
            "Hed_EYE005": "ダイバーゴーグル",
            "Hed_EYE006": "アローバンド ホワイト",
            "Hed_EYE007": "ダテコンタクト",
            "Hed_EYE008": "タレサン18K",
            "Hed_EYE009": "マルベッコー",
            "Hed_EYE010": "オクタグラス",
            "Hed_EYE011": "セルブロウ",
            "Hed_EYE012": "ダブルエッグサングラス",
            "Hed_EYE013": "エゾッコフリッパー",
            "Hed_EYE014": "マルサンSV925",
            "Hed_EYE015": "アナアキバスクベレー",
            "Hed_EYE016": "スイミングモーグル",
            "Hed_EYE017": "スミガードゴーグル",
            "Hed_EYE018": "モーグル タタキベッチュー",
            "Hed_EYE019": "センニューゴーグル",
            "Hed_EYE020": "センニュークロブチ",
            "Hed_FST000": "ヘッドバンド ホワイト",
            "Hed_HAP000": "キョンキョンぼう",
            "Hed_HAP001": "ウミウシカチューシャ",
            "Hed_HAP002": "ホッケかめん",
            "Hed_HAP003": "アンコウラバーマスク",
            "Hed_HAP004": "パーティーコーンデコ",
            "Hed_HAP005": "ニューイヤーグラスDX",
            "Hed_HAP006": "ねじりゴージャス",
            "Hed_HAP007": "ハッピーチンアナゴハット",
            "Hed_HAP008": "ノベルティバイザールピナス",
            "Hed_HAP009": "ノベルティバイザーナズナ",
            "Hed_HAP010": "ノベルティバイザーポピー",
            "Hed_HAP011": "ノベルティバイザーナデシコ",
            "Hed_HAP012": "バーニングブロイラー",
            "Hed_HAP013": "ギガギョコツ",
            "Hed_HAP014": "コズミックアンテナ",
            "Hed_HAP015": "ジャスティスブレイン ",
            "Hed_HAT000": "ロブスターブーニー",
            "Hed_HAT001": "サファリハット",
            "Hed_HAT002": "キャンプハット",
            "Hed_HAT003": "フグベルハット",
            "Hed_HAT004": "スゲ",
            "Hed_HAT005": "イカンカン",
            "Hed_HAT006": "イカンカン クラシック",
            "Hed_HAT007": "トレジャーメット",
            "Hed_HAT008": "イカバケット",
            "Hed_HAT009": "パッチハット",
            "Hed_HAT010": "パラソルチューリップ",
            "Hed_HAT011": "フグベルベルハット",
            "Hed_HAT012": "カイガラスゲ",
            "Hed_HAT013": "ホタプラントハット",
            "Hed_HAT014": "ヤマハット",
            "Hed_HBD001": "バスケバンド",
            "Hed_HBD002": "スカッシュバンド",
            "Hed_HBD003": "テニスバンド",
            "Hed_HBD004": "ランニングバンド",
            "Hed_HBD005": "サッカーバンド",
            "Hed_HBD007": "ヤキフグビスケットバンダナ",
            "Hed_HBD008": "クロヤキフグバンダナ",
            "Hed_HDP000": "スタジオヘッドホン",
            "Hed_HDP001": "オーロラヘッドホン",
            "Hed_HDP002": "イヤーマフ",
            "Hed_HDP003": "エンペラフックHDP",
            "Hed_HDP004": "ステカセヘッドホン",
            "Hed_HDP005": "スタジオオクトホン",
            "Hed_HDP006": "センニューヘッドホン",
            "Hed_MET000": "サイクルメット",
            "Hed_MET002": "ナイトビジョン",
            "Hed_MET003": "テンタクルズメット",
            "Hed_MET004": "スケボーメット",
            "Hed_MET005": "バイザーメット",
            "Hed_MET006": "ロゴヅクシMTBメット",
            "Hed_MET007": "イカロスHKメット",
            "Hed_MET008": "ツヤケシMTBメット",
            "Hed_MET009": "オクトメットプライズデコ",
            "Hed_MET010": "モイストワカメット",
            "Hed_MET011": "デカメットアイシールド",
            "Hed_MSK000": "タコマスク",
            "Hed_MSK001": "フェイスゴーグル",
            "Hed_MSK002": "エイズリーバンダナ",
            "Hed_MSK003": "イカスカルマスク",
            "Hed_MSK004": "ペインターマスク",
            "Hed_MSK005": "アナアキマスク",
            "Hed_MSK006": "キングタコスターマスク",
            "Hed_MSK007": "イカバッテンガード",
            "Hed_MSK008": "マスクドホッコリー",
            "Hed_MSK009": "キングオブマスク",
            "Hed_MSK010": "ノーズガードモトクロス",
            "Hed_MSK011": "フォーリマスク",
            "Hed_MSK012": "フォーリマスク デジカモ",
            "Hed_MSK013": "こうしえんバンダナ",
            "Hed_MSN000": "ヒーローヘッズ レプリカ",
            "Hed_MSN004": "アーマーメット レプリカ",
            "Hed_MSN101": "ヒーローレシーバー レプリカ",
            "Hed_MSN104": "タコゾネスサングラス",
            "Hed_MSN105": "ネルメット レプリカ",
            "Hed_MSN106": "グランパなアタマ",
            "Hed_MSN107": "メトロぼう",
            "Hed_MSN108": "金のつまようじ",
            "Hed_NCP000": "ボンボンニット",
            "Hed_NCP001": "ショートビーニー",
            "Hed_NCP002": "ボーダービーニー",
            "Hed_NCP003": "ウインターボンボン",
            "Hed_NCP004": "モンゴウベレー",
            "Hed_NCP005": "イカノルディック",
            "Hed_NCP006": "センニューボンボン",
            "Hed_NCP008": "リブニット",
            "Hed_NCP009": "アナアキアンピンベレー",
            "Hed_NCP010": "ヤマギリビーニー",
            "Hed_NCP011": "オシノビニット",
            "Hed_RVL000": "タコゾネススコープ",
            "Hed_VIS000": "キャディ サンバイザー",
            "Hed_VIS001": "ヤキフグ サンバイザー",
            "Hed_VIS002": "サンサンサンバイザー",
            "Hed_VIS003": "ヤコバイザー",
            "Hed_VIS004": "フェイスバイザー"
        },
        "clothes_body": {
            "Clt_AMB000": "スクールブレザー",
            "Clt_AMB001": "サムライジャケット",
            "Clt_AMB002": "パワードスーツ",
            "Clt_AMB003": "スクールカーデ",
            "Clt_AMB004": "ニンジャスーツ",
            "Clt_AMB005": "パワードスーツ オリジン",
            "Clt_AMB006": "ヒメイトパーカー",
            "Clt_AMB007": "イイダチトップス",
            "Clt_AMB008": "エンチャントローブ",
            "Clt_AMB009": "タコティカルなよろい",
            "Clt_AMB010": "ひれおくんのて",
            "Clt_COP100": "イカテンくんポロ",
            "Clt_COP101": "アンカーベスト",
            "Clt_COP102": "フューエルブルゾン",
            "Clt_COP103": "マクレGT",
            "Clt_COP104": "アゲアゲ・10・プラーXXL",
            "Clt_COP105": "フロムキタグニ87",
            "Clt_COP106": "ゾネスティックプロテクター",
            "Clt_COP107": "レコヤルックEP",
            "Clt_COP108": "デベロッパーズワークウエア",
            "Clt_COP109": "ジムパーソンアーマー",
            "Clt_COP110": "アカシックコート",
            "Clt_CRC000": "メカボディ・AKM",
            "Clt_FST001": "わかばイカＴ",
            "Clt_FST002": "わかばタコT",
            "Clt_HAP001": "フェスＴ",
            "Clt_HAP002": "フェスＴ レプリカ",
            "Clt_JKT000": "マウンテンオリーブ",
            "Clt_JKT001": "ヤコナイロン ヴィンテージ",
            "Clt_JKT002": "マウンテンベリー",
            "Clt_JKT003": "スタジャンロゴマシ",
            "Clt_JKT004": "スクールジャージー",
            "Clt_JKT005": "レタード グリーン",
            "Clt_JKT006": "イカライダーBLACK",
            "Clt_JKT007": "イカライダーWHITE",
            "Clt_JKT008": "FCジャージー",
            "Clt_JKT009": "レタード オレンジ",
            "Clt_JKT010": "F-190",
            "Clt_JKT011": "F-010",
            "Clt_JKT012": "イカセーラー ブルー",
            "Clt_JKT013": "イカセーラー ホワイト",
            "Clt_JKT014": "イカスカジャン",
            "Clt_JKT015": "ウラスカジャン",
            "Clt_JKT016": "クラーゲス528",
            "Clt_JKT017": "マウンテンフローズン",
            "Clt_JKT018": "ヤコナイロンレトロ",
            "Clt_JKT019": "マッチャ ライトダウン",
            "Clt_JKT020": "FA-01オモテ",
            "Clt_JKT021": "FA-01ウラ",
            "Clt_JKT022": "プルオーバーコート",
            "Clt_JKT023": "ケンサキコーチ",
            "Clt_JKT024": "トリスカベッチン",
            "Clt_JKT025": "ウラタコスカジャン",
            "Clt_JKT026": "エゾッココーチ アカネ",
            "Clt_JKT027": "マウンテンノリタマゴ",
            "Clt_JKT028": "エゾッココーチ モエギ",
            "Clt_JKT029": "ボンバージャケット ポジ",
            "Clt_JKT030": "FA-11オモテ カスタム",
            "Clt_JKT031": "FA-11ウラ カスタム",
            "Clt_JKT032": "キングベンチカイザー",
            "Clt_JKT033": "キングベンチNV",
            "Clt_JKT034": "エゾッココーチ ウコン",
            "Clt_JKT035": "F-3 ペイントカスタム",
            "Clt_JKT036": "ボンバージャケット ネガ",
            "Clt_JKT037": "モイストギリースーツ",
            "Clt_JKT038": "F-3 ホワイトレザー",
            "Clt_JKT039": "マウンテンチリペッパー",
            "Clt_JKT040": "ハウスタグホエールニット",
            "Clt_JKT041": "ロッケンブレイクジャケット",
            "Clt_JKT042": "クンフージャージ",
            "Clt_JKT043": "クンフーパンジャージ",
            "Clt_JKT044": "センニュースーツ",
            "Clt_MSN000": "ヒーロージャケット レプリカ",
            "Clt_MSN004": "アーマージャケット レプリカ",
            "Clt_MSN101": "ヒーローフーディー レプリカ",
            "Clt_MSN104": "タコゾネスプロテクターネオ",
            "Clt_MSN105": "ネルアーマー レプリカ",
            "Clt_MSN106": "グランパなフク",
            "Clt_PLO000": "さくらエビポロ",
            "Clt_PLO001": "オレンジボーダーラガー",
            "Clt_PLO002": "トリコロールラガー",
            "Clt_PLO003": "よもぎポロ",
            "Clt_PLO004": "ピンポンポロ",
            "Clt_PLO005": "テッカサイクルシャツ",
            "Clt_PLO006": "チャリキングジャージ",
            "Clt_PLO007": "FCカラスミ",
            "Clt_PLO008": "アオサドーレ",
            "Clt_PRK000": "ジップアップ カモ",
            "Clt_PRK001": "ジップアップ グリーン",
            "Clt_PRK002": "エゾッコパーカー アズキ",
            "Clt_PRK004": "シャツノゾキブルー",
            "Clt_PRK005": "キングパーカー グレープ",
            "Clt_PRK006": "ホタパーカー グレー",
            "Clt_PRK007": "ホタプラントパーカー",
            "Clt_PRK008": "シャツノゾキピンク",
            "Clt_PRK009": "エゾッコパーカー ウグイス",
            "Clt_PRK010": "ホタパーカー ブラック",
            "Clt_PRK011": "おうえんパーカー(タコver.)",
            "Clt_RVL000": "タコゾネスプロテクター",
            "Clt_SHT000": "オータムネル",
            "Clt_SHT001": "イカスタンシャツ",
            "Clt_SHT002": "ギンガムチェック ミドリ",
            "Clt_SHT003": "シロシャツ",
            "Clt_SHT004": "ウーニーズBBシャツ",
            "Clt_SHT005": "おどるイカアロハ",
            "Clt_SHT006": "ギンガムチェック アカ",
            "Clt_SHT007": "ベイビークラゲシャツ",
            "Clt_SHT008": "ミスターベースボール",
            "Clt_SHT009": "ミックスシャツ グレー",
            "Clt_SHT010": "ヴィンテージチェック",
            "Clt_SHT011": "マルエリシャツ",
            "Clt_SHT012": "ロゴマシマシアロハ",
            "Clt_SHT013": "ブロックストライプシャツ",
            "Clt_SHT014": "シャンブレーシャツ",
            "Clt_SHT015": "タイシャツ",
            "Clt_SHT017": "ピーターパンクシャツ",
            "Clt_SHT018": "タコボウラーシャツ",
            "Clt_SHT019": "スミカケシャツ",
            "Clt_SHT020": "パラシューター ザクロ",
            "Clt_SHT021": "タイツキベイビークラゲ",
            "Clt_SHT022": "パラシューター プルーン",
            "Clt_SHT023": "ピーターパンクタイ ブラッド",
            "Clt_SHT024": "チリメンタコアロハ",
            "Clt_SHT025": "アナアキオンブレネル",
            "Clt_SHT026": "スミヌキシャツ",
            "Clt_SHT027": "レイヤードットシャツ",
            "Clt_SHT028": "タタキBBBシャツ",
            "Clt_SHT029": "BBシャツ プレミアム",
            "Clt_SWT000": "カレッジスウェット グレー",
            "Clt_SWT001": "イカバッテン マスタード",
            "Clt_SWT002": "レトロジャッジ",
            "Clt_SWT003": "ホッコリー ネイビー",
            "Clt_SWT004": "カレッジスウェット ネイビー",
            "Clt_SWT005": "リールロールスウェット",
            "Clt_SWT006": "イカリスウェット",
            "Clt_SWT007": "ドロップスウェット ネガ",
            "Clt_SWT008": "ショートニットカサネ",
            "Clt_SWT009": "ドロップスウェット ポジ",
            "Clt_SWT010": "アナアキニット アオソデ",
            "Clt_SWT011": "アナアキニット キソデ",
            "Clt_SWT012": "アナアキニット アカソデ",
            "Clt_SWT013": "エンペーサートレーナー",
            "Clt_SWT014": "オクタリアンレトロ",
            "Clt_SWT015": "ヤコピステ",
            "Clt_TEL000": "ボーダーホワイト",
            "Clt_TEL001": "バニーポップ ブラック",
            "Clt_TEL002": "カモフラパープル",
            "Clt_TEL003": "ボーダーネイビー",
            "Clt_TEL004": "エゾッコラグラン",
            "Clt_TEL005": "カレッジラグラン",
            "Clt_TEL006": "ハラグロラグラン",
            "Clt_TEL007": "ハラシロラグラン",
            "Clt_TEL008": "バトロング ホワイト",
            "Clt_TEL009": "ボーダーモスグリーン",
            "Clt_TEL010": "イカバッテンロング",
            "Clt_TEL011": "アイロニックロング",
            "Clt_TEL012": "ヤマビコボーダー",
            "Clt_TEL013": "ゆとりボーダー ピンク",
            "Clt_TEL014": "トビウォーズHKユニ",
            "Clt_TEL015": "アナアキロンT ドライブ",
            "Clt_TEL016": "ゆとりボーダー ライム",
            "Clt_TEL017": "アナアキロンT イボルブ",
            "Clt_TEL018": "エゾッコロンTキャロット",
            "Clt_TEL019": "エゾッコロンTラディッシュ",
            "Clt_TEL020": "タコロンT 黒",
            "Clt_TEL021": "ヤコラグランクレイジー",
            "Clt_TEL022": "タコロンT 赤",
            "Clt_TEL023": "ヤキフグ16bit カーキ",
            "Clt_TEL024": "ヤキフグ16bit ブルー",
            "Clt_TES000": "イカホワイト",
            "Clt_TES001": "イカノメＴ ブラック",
            "Clt_TES003": "イカノメＴ ライトブルー",
            "Clt_TES004": "ロッケンベルグＴ ホワイト",
            "Clt_TES005": "ロッケンベルグＴ ブラック",
            "Clt_TES006": "イカブラック",
            "Clt_TES007": "サニーオレンジＴ",
            "Clt_TES008": "レイニーブルーＴ",
            "Clt_TES009": "イカジャマイカ",
            "Clt_TES010": "マルフグＴ",
            "Clt_TES011": "ミントＴ",
            "Clt_TES012": "グレープＴ",
            "Clt_TES013": "ベクトルパターン レッド",
            "Clt_TES014": "ベクトルパターン グレー",
            "Clt_TES015": "ヤマビコＴ ブルー",
            "Clt_TES016": "ヤマビコＴ アイボリー",
            "Clt_TES017": "チドリメロンＴ",
            "Clt_TES018": "パイレーツボーダー",
            "Clt_TES019": "マリンボーダー",
            "Clt_TES020": "ヤキフグ8bit ホワイト",
            "Clt_TES021": "ヤキフグ8bit ブラック",
            "Clt_TES022": "ガチホワイト",
            "Clt_TES023": "ガチブラック",
            "Clt_TES026": "ニクショクＴ",
            "Clt_TES027": "パールドットＴ",
            "Clt_TES028": "タコＴ",
            "Clt_TES029": "ソウショクＴ",
            "Clt_TES030": "イカブラックV",
            "Clt_TES031": "デカロゴＴ シロ",
            "Clt_TES032": "スウェットT ゴブ",
            "Clt_TES033": "キングHKシャツ",
            "Clt_TES034": "ヤキフグ8bit グレー",
            "Clt_TES035": "イカホワイトV",
            "Clt_TES036": "ガンガゼロックT シロ",
            "Clt_TES037": "ガンガゼロックT クロ",
            "Clt_TES038": "バンドT WETFLOOR",
            "Clt_TES039": "バンドT SQUIDSQUAD",
            "Clt_TES040": "デカロゴT ノーコン",
            "Clt_TES041": "ミスターシュラッグT",
            "Clt_TES042": "バンドT ABXY",
            "Clt_TES043": "バンドT HIGHTIDEERA",
            "Clt_TES044": "イカレッドV コラボ",
            "Clt_TES045": "イカグリーンV コラボ",
            "Clt_TES046": "ω-3T",
            "Clt_TES047": "アナアキT ポルポピック",
            "Clt_TES048": "ホットグラデT",
            "Clt_TES049": "ヤコタイダイ ギャラクシー",
            "Clt_TES050": "ヤコタイダイ レインボー",
            "Clt_TES051": "ミズシュラッグT",
            "Clt_TES052": "リーグT",
            "Clt_TES053": "フレンドT",
            "Clt_TES054": "アロメスローガンT",
            "Clt_TES055": "アイスグラデT",
            "Clt_TES056": "キングオクトHKシャツ",
            "Clt_TES057": "デカロTキウイ",
            "Clt_TES058": "デカロTゴールデン",
            "Clt_TES059": "キングオクトTブラックベロア",
            "Clt_TES060": "キングオクトTミドリベロア",
            "Clt_TES061": "SWCロゴT",
            "Clt_TLY000": "レイヤード ホワイト",
            "Clt_TLY001": "マスタードガサネ",
            "Clt_TLY002": "カモガサネ",
            "Clt_TLY003": "レイヤード ブラック",
            "Clt_TLY004": "アイロニックレイヤード",
            "Clt_TLY005": "ガチガサネ",
            "Clt_TLY006": "チョコガサネ",
            "Clt_TLY007": "かくれパイレーツ",
            "Clt_TLY008": "ベクトルラインガサネ",
            "Clt_TLY009": "グリーンＴ",
            "Clt_TLY010": "アロメテックT レッド",
            "Clt_TLY011": "アロメテックT ブルー",
            "Clt_TLY012": "オクトガサネ",
            "Clt_TLY013": "イカイエローVガサネ",
            "Clt_TNK000": "バスケジャージ ホーム",
            "Clt_TNK001": "バスケジャージ アウェイ",
            "Clt_TNK003": "キングタンク ホワイト",
            "Clt_TNK004": "キングタンク スラッシュ",
            "Clt_TNK005": "キングタンク マリン",
            "Clt_TNK006": "ロブスターズユニ",
            "Clt_VST000": "マウンテンダウン",
            "Clt_VST001": "フォレストダウン",
            "Clt_VST002": "アーバンベスト ナイト",
            "Clt_VST003": "アーバンベスト イエロー",
            "Clt_VST004": "イカゴッチンベスト",
            "Clt_VST005": "イカノボリベスト",
            "Clt_VST007": "フィッシャーズベスト オジ",
            "Clt_VST008": "フロントジップベスト",
            "Clt_VST009": "アロメランベスト シルバー"
        },
        "clothes_shoes": {
            "Shs_AMB000": "スクールローファー",
            "Shs_AMB001": "サムライシューズ",
            "Shs_AMB002": "パワードレッグス",
            "Shs_AMB003": "キルトローファー",
            "Shs_AMB004": "シノビアシ",
            "Shs_AMB005": "パワードレッグス オリジン",
            "Shs_AMB006": "ヒメイトスニーカー",
            "Shs_AMB007": "イイダチスリッポン",
            "Shs_AMB008": "エンチャントブーツ",
            "Shs_AMB009": "タコティカルなすねあて",
            "Shs_AMB010": "ひれおくんのあし",
            "Shs_BOT000": "モトクロスブーツ",
            "Shs_BOT001": "ヌバックブーツ イエロー",
            "Shs_BOT002": "ヌバックブーツ レッド",
            "Shs_BOT003": "モトクロス ソリッドブルー",
            "Shs_BOT004": "レイニーモスグリーン",
            "Shs_BOT005": "レイニーアセロラ",
            "Shs_BOT006": "ロッキンホワイト",
            "Shs_BOT007": "ロッキンチェリー",
            "Shs_BOT008": "ロッキンイエロー",
            "Shs_BOT009": "レイニーシャボン",
            "Shs_BOT010": "ミルキーダウンブーツ",
            "Shs_BOT011": "アイスダウンブーツ",
            "Shs_BOT012": "ハンティングブーツ",
            "Shs_BOT013": "ロッキンブラック",
            "Shs_BOT014": "シンカイレザーブーツ",
            "Shs_BOT015": "モイストコンブーツ",
            "Shs_BOT016": "アナアキスパイダー6ホール",
            "Shs_BOT017": "シンリョクレザーブーツ",
            "Shs_BOT018": "チャバハンティングブーツ",
            "Shs_CFS000": "ブルーベリーコンフォート",
            "Shs_CFS001": "アケビコンフォート",
            "Shs_COP101": "マッドラバー",
            "Shs_COP102": "ノンスリップタクミ",
            "Shs_COP103": "ゾネスティックブーツ",
            "Shs_COP104": "チギリノヒモ",
            "Shs_COP105": "ゲソバタアシスト",
            "Shs_COP106": "バンカラコロン",
            "Shs_CRC000": "メカレッグ・IBS",
            "Shs_FST000": "キャンバス ホワイト",
            "Shs_HAP000": "ノーリーチャッカ ヒメイト",
            "Shs_HAP001": "エギング4 ヒメキン",
            "Shs_HAP002": "ロッキンクラウン",
            "Shs_HAP003": "アカツキアローズ",
            "Shs_HAP004": "ノーリーチャッカ イイダチ",
            "Shs_HAP005": "エギング4 イイマリ",
            "Shs_HAP006": "パワーストリップ トルーパー",
            "Shs_HAP007": "ミッドナイトスリッポン",
            "Shs_LTS000": "ラバーソール ホワイト",
            "Shs_LTS001": "ラバーソール チェリー",
            "Shs_LTS002": "ラバーソール ターコイズ",
            "Shs_LTS003": "イカスミチップ",
            "Shs_LTS004": "イカヤキチップ",
            "Shs_LTS005": "イカボウズキャメル",
            "Shs_LTS006": "スモークチップ",
            "Shs_LTS007": "ネイビーチップ レッドソール",
            "Shs_LTS008": "グレーチップ イエローソール",
            "Shs_LTS009": "イカボウズジェットブラック",
            "Shs_LTS010": "アナアキラバー ハバネロ",
            "Shs_LTS011": "アナアキラバー フェイク",
            "Shs_LTS012": "センニューチップ スミソール",
            "Shs_MSN000": "ヒーローキックス レプリカ",
            "Shs_MSN004": "アーマーブーツ レプリカ",
            "Shs_MSN101": "ヒーローバインダー レプリカ",
            "Shs_MSN104": "タコゾネスブーツネオ",
            "Shs_MSN105": "ネルブーツ レプリカ",
            "Shs_MSN106": "グランパなクツ",
            "Shs_RVL000": "タコゾネスブーツ",
            "Shs_SDL000": "オイスタークロッグ",
            "Shs_SDL001": "チョコクロッグ",
            "Shs_SDL003": "デルタストラップ ネオン",
            "Shs_SDL004": "BBサンダル",
            "Shs_SDL005": "デルタストラップ スノー",
            "Shs_SDL006": "デルタストラップ ルミナス",
            "Shs_SDL007": "ヤキフグシャワサン アカ",
            "Shs_SDL008": "ヤキフグシャワサン キ",
            "Shs_SDL009": "フジツボペタサン",
            "Shs_SHI000": "シーホースHi レッド",
            "Shs_SHI001": "シーホースHi ゾンビ",
            "Shs_SHI002": "キャンバスHi マッシュルーム",
            "Shs_SHI003": "シーホースHi パープル",
            "Shs_SHI004": "キャンバスHi モロヘイヤ",
            "Shs_SHI005": "キャンバスHi トマト",
            "Shs_SHI006": "シーホースHi ゴールド",
            "Shs_SHI008": "シャークモカシン",
            "Shs_SHI009": "ジョーズモカシン",
            "Shs_SHI010": "デカロニックチョコレート",
            "Shs_SHI011": "デカロニックミント",
            "Shs_SHI012": "デカロニックブラック",
            "Shs_SHI013": "ピラニアモカシン",
            "Shs_SHI014": "ノリマキ750 ホワイト",
            "Shs_SHI015": "ノリマキ750 ブラック",
            "Shs_SHI016": "オルカHiサンセット",
            "Shs_SHI017": "エギング4 アカクロ",
            "Shs_SHI018": "エギング4 アオクロ",
            "Shs_SHI019": "ウミウシタウンHi グレー",
            "Shs_SHI020": "オルカHi",
            "Shs_SHI021": "エンペリアルカイザー",
            "Shs_SHI022": "エンペリアルNV",
            "Shs_SHI023": "ウミウシタウンHi アンバー",
            "Shs_SHI024": "イロマキ750 イエロー",
            "Shs_SHI025": "エギング5 シロアカ",
            "Shs_SHI026": "エギング5 ハニオレ",
            "Shs_SHI027": "エギング4 キイコン",
            "Shs_SHI028": "オルカHiウーブン",
            "Shs_SHI029": "イロマキ750 グリーン",
            "Shs_SHI030": "イロマキ750 パープル",
            "Shs_SHI031": "イロマキ750 レッド",
            "Shs_SHI032": "イロマキ750 ブルー",
            "Shs_SHI033": "イロマキ750 オレンジ",
            "Shs_SHI034": "パワーストリップ アカアシ",
            "Shs_SHI035": "パワーストリップ アオアシ",
            "Shs_SHI036": "ストリップ タタキベッチュー",
            "Shs_SHI037": "ゴマシオ270",
            "Shs_SHI038": "エギング5 クロアオ",
            "Shs_SHI039": "オルカHiパッション",
            "Shs_SHI040": "キャンバスHi トリュフ",
            "Shs_SHI041": "エギング5 プレミアム",
            "Shs_SHT000": "ピンクビーンズ",
            "Shs_SHT001": "オレンジアローズ",
            "Shs_SHT002": "ウミウシイエロー",
            "Shs_SHT003": "ホワイトアローズ",
            "Shs_SHT004": "シアンビーンズ",
            "Shs_SHT005": "ウミウシブルー",
            "Shs_SHT006": "ウミウシレッド",
            "Shs_SHT007": "ウミウシパープル",
            "Shs_SHT008": "クレイジーアローズ",
            "Shs_SHT009": "ブラックビーンズ",
            "Shs_SHT010": "スミレビーンズ",
            "Shs_SHT011": "カナリアビーンズ",
            "Shs_SHT012": "アロメッシュイエロー",
            "Shs_SHT013": "アローズ タタキベッチュー",
            "Shs_SHT014": "アロメッシュバーミリオン",
            "Shs_SHT015": "エンペーサーCaO",
            "Shs_SHT016": "エンペーサーAg",
            "Shs_SHT017": "エンペーサーAu",
            "Shs_SHT018": "ウミウシボルト95",
            "Shs_SHT019": "アスレチックアローズ",
            "Shs_SLO000": "グリッチョ ブルー",
            "Shs_SLO001": "キャンバス バナナ",
            "Shs_SLO002": "グリッチョ グリーン 限定版",
            "Shs_SLO003": "シーホース ホワイト",
            "Shs_SLO004": "グリッチョ オレンジ",
            "Shs_SLO005": "シーホース ブラックレザー",
            "Shs_SLO006": "キャンバス クマノミ",
            "Shs_SLO007": "シーホース イエロー",
            "Shs_SLO008": "ベリベリホワイト",
            "Shs_SLO009": "ベリベリレッド",
            "Shs_SLO010": "ユデスパイカ",
            "Shs_SLO011": "レアスパイカ",
            "Shs_SLO012": "ボルダーシューズ タイノエ",
            "Shs_SLO013": "ボルダーシューズ ハザクラ",
            "Shs_SLO014": "ヒモヒモグリーン",
            "Shs_SLO015": "デカロノーレース ホワイト",
            "Shs_SLO016": "デカロノーレース ブルー",
            "Shs_SLO017": "ノーリーチャッカ グレー",
            "Shs_SLO018": "ノーリーチャッカ トライブ",
            "Shs_SLO019": "ノーリーチャッカ ロビンズ",
            "Shs_SLO020": "スパイカ タタキベッチュー",
            "Shs_SLP000": "スリッポン ブルー",
            "Shs_SLP001": "スリッポン レッド",
            "Shs_SLP002": "スリッポン チドリ",
            "Shs_SLP003": "スリッポン ポルカ",
            "Shs_TRS000": "トレッキングライト",
            "Shs_TRS001": "トレッキングカスタム",
            "Shs_TRS002": "トレッキングプロ"
        },
        "stage": {
            "Fld_Amida01_Vss": "ホッケふ頭",
            "Fld_Athletic01_Vss": "モンガラキャンプ場",
            "Fld_Carousel00_Vss": "スメーシーワールド",
            "Fld_Court00_Vss": "アジフライスタジアム",
            "Fld_Deli_Octa00_02_Vss": "ウィンドミル・キス",
            "Fld_Deli_Octa01_2_Vss": "追憶のスライド",
            "Fld_Deli_Octa02_2_Vss": "約束の丘で会いましょう",
            "Fld_Deli_Octa03_2_Vss": "ハンサムなスポンジ",
            "Fld_Deli_Octa05_Vss": "ヒメちゃんのキャノン",
            "Fld_Deli_Octa06_Vss": "トランスペアレント・ボーイ",
            "Fld_Deli_Octa07_Vss": "バーの一族",
            "Fld_Deli_Octa08_Vss": "イタズラなヒキヨセ",
            "Fld_Deli_Octa09_Vss": "あしたはデンデン",
            "Fld_Deli_Octa10_Vss": "トジトジ",
            "Fld_Deli_Octa11_Vss": "天秤ラヴァーズ",
            "Fld_Deli_Octa12_Vss": "ヌリとスイッチの吐息",
            "Fld_Deli_Octa13_Vss": "たこあし注意報！",
            "Fld_Deli_Octa14_Vss": "ジャンプマットの詩",
            "Fld_Deli_Octa15_Vss": "キミのハートにライド・オン！",
            "Fld_Deli_Octa16_Vss": "カンケツセンのばら",
            "Fld_Deli_Octa17_Vss": "恋はダッシュ×３",
            "Fld_Deli_Octa18_Vss": "ドーザームーン",
            "Fld_Deli_Octa19_Vss": "クイックバスケット",
            "Fld_Deli_Octa20_Vss": "ヌリヌリトゥナイト",
            "Fld_Deli_Octa21_Vss": "ビッグ＝パネルが止まらない",
            "Fld_Deli_Octa22_Vss": "思い出コロガリウム",
            "Fld_Deli_Octa23_Vss": "ピロピロなんかじゃない",
            "Fld_Deli_Octa24_Vss": "DEAR SENPAI",
            "Fld_Deli_Vss": "ミステリーゾーン",
            "Fld_Ditch02_Vss": "バッテラストリート",
            "Fld_Kawa00_Vss": "エンガワ河川敷",
            "Fld_Line00_Vss": "ザトウマーケット",
            "Fld_Maze01_Vss": "モズク農園",
            "Fld_Maze02_Vss": "モズク農園",
            "Fld_Mirror00_Vss": "ムツゴ楼",
            "Fld_Nagasaki00_Vss": "チョウザメ造船",
            "Fld_Nakasu00_Vss": "ホテルニューオートロ",
            "Fld_Nakasu02_Vss": "ホテルニューオートロ",
            "Fld_Office01_Vss": "アンチョビットゲームズ",
            "Fld_Pillar00_Vss": "マンタマリア号",
            "Fld_Quarry01_Vss": "ショッツル鉱山",
            "Fld_Shakehouse00_Cop": "海上集落シャケト場",
            "Fld_Shakelift00_Cop": "トキシラズいぶし工房",
            "Fld_Shakeride00_Cop": "朽ちた箱舟 ポラリス",
            "Fld_Shakeship00_Cop": "難破船ドン・ブラコ",
            "Fld_Shakeup00_Cop": "シェケナダム",
            "Fld_SkatePark02_Vss": "Ｂバスパーク",
            "Fld_Tunnel00_Vss": "デボン海洋博物館",
            "Fld_Tunnel02_Vss": "デボン海洋博物館",
            "Fld_Tuzura00_Vss": "タチウオパーキング",
            "Fld_Unduck00_Vss": "フジツボスポーツクラブ",
            "Fld_UpDown01_Vss": "アロワナモール",
            "Fld_Upland00_Vss": "海女美術大学",
            "Fld_Venue02_Vss": "ガンガゼ野外音楽堂",
            "Fld_Warehouse01_Vss": "ハコフグ倉庫",
            "Fld_Wave00_Vss": "コンブトラック"
        },
        "main_power_explain": {
            "MPU_BrushSpeedUp": "塗りながら進む速度が\nわずかにアップします。",
            "MPU_CanopyHPUp": "カサの耐久力がアップします。",
            "MPU_CanopyRecoveryUp": "カサが復活するまでの時間が\n短くなります。",
            "MPU_DamageAreaUp": "爆風で大ダメージをあたえる\n範囲が広がります。",
            "MPU_DamageReductionDown": "最大ダメージをあたえられる\n距離が長くなります。",
            "MPU_DamageUp": "あたえるダメージが大きくなります。",
            "MPU_PaintUp": "塗り性能がアップします。",
            "MPU_RangeUp": "弾がわずかに遠くまで\n飛ぶようになります。",
            "MPU_ReduceDegJump": "ジャンプして射撃したときの弾が\nブレにくくなります。",
            "MPU_ShootingFrameUp": "射撃継続時間が\n長くなります。"
        },
        "mode": {
            "cFes": "ナワバリバトル（フェス）",
            "cPnt": "ナワバリバトル",
            "cVar": "ガチエリア",
            "cVcl": "ガチアサリ",
            "cVgl": "ガチホコバトル",
            "cVlf": "ガチヤグラ"
        }
    }
}